{"items":[{"id":"n1","title":"Lancio della piattaforma 2.0","excerpt":"Nuove funzionalità per affidabilità, osservabilità e scala globale.","image":"/img/hero.svg","url":"#","date":"2025-08-20T09:00:00Z"},{"id":"n2","title":"Accordo strategico con partner internazionali","excerpt":"Espandiamo la presenza in 18 nuovi mercati con SLA locali.","image":"/img/logo.svg","url":"#","date":"2025-08-12T10:30:00Z"},{"id":"n3","title":"Report prestazioni H1","excerpt":"Riduzione del 37% della latenza p95 e uptime del 99.99%.","image":"/img/hero.svg","url":"#","date":"2025-07-28T08:00:00Z"}]}